<annotation>
	<folder>001plate</folder>
	<filename>m570_2.jpg</filename>
	<path>/home/theophile/Desktop/Plate-Detection/darkflow/data/Images/001plate/m570_2.jpg</path>
	<source>
		<database>Unknown</database>
	</source>
	<size>
		<width>3024</width>
		<height>4032</height>
		<depth>3</depth>
	</size>
	<segmented>0</segmented>
	<object>
		<name>plate</name>
		<pose>Unspecified</pose>
		<truncated>0</truncated>
		<difficult>0</difficult>
		<bndbox>
			<xmin>1022</xmin>
			<ymin>2068</ymin>
			<xmax>2318</xmax>
			<ymax>2789</ymax>
		</bndbox>
	</object>
</annotation>
