<annotation>
	<folder>cropped_img_plate</folder>
	<filename>m587_1.jpg</filename>
	<path>/Users/jordanvaneetveldt/Downloads/cropped_img_plate/m587_1.jpg</path>
	<source>
		<database>Unknown</database>
	</source>
	<size>
		<width>1250</width>
		<height>584</height>
		<depth>3</depth>
	</size>
	<segmented>0</segmented>
	<object>
		<name>1</name>
		<pose>Unspecified</pose>
		<truncated>0</truncated>
		<difficult>0</difficult>
		<bndbox>
			<xmin>118</xmin>
			<ymin>324</ymin>
			<xmax>241</xmax>
			<ymax>503</ymax>
		</bndbox>
	</object>
	<object>
		<name>U</name>
		<pose>Unspecified</pose>
		<truncated>0</truncated>
		<difficult>0</difficult>
		<bndbox>
			<xmin>373</xmin>
			<ymin>251</ymin>
			<xmax>513</xmax>
			<ymax>436</ymax>
		</bndbox>
	</object>
	<object>
		<name>W</name>
		<pose>Unspecified</pose>
		<truncated>0</truncated>
		<difficult>0</difficult>
		<bndbox>
			<xmin>510</xmin>
			<ymin>219</ymin>
			<xmax>635</xmax>
			<ymax>408</ymax>
		</bndbox>
	</object>
	<object>
		<name>R</name>
		<pose>Unspecified</pose>
		<truncated>0</truncated>
		<difficult>0</difficult>
		<bndbox>
			<xmin>635</xmin>
			<ymin>198</ymin>
			<xmax>764</xmax>
			<ymax>379</ymax>
		</bndbox>
	</object>
	<object>
		<name>9</name>
		<pose>Unspecified</pose>
		<truncated>0</truncated>
		<difficult>0</difficult>
		<bndbox>
			<xmin>891</xmin>
			<ymin>136</ymin>
			<xmax>1008</xmax>
			<ymax>312</ymax>
		</bndbox>
	</object>
	<object>
		<name>9</name>
		<pose>Unspecified</pose>
		<truncated>0</truncated>
		<difficult>0</difficult>
		<bndbox>
			<xmin>1016</xmin>
			<ymin>101</ymin>
			<xmax>1127</xmax>
			<ymax>278</ymax>
		</bndbox>
	</object>
	<object>
		<name>2</name>
		<pose>Unspecified</pose>
		<truncated>0</truncated>
		<difficult>0</difficult>
		<bndbox>
			<xmin>1135</xmin>
			<ymin>73</ymin>
			<xmax>1238</xmax>
			<ymax>263</ymax>
		</bndbox>
	</object>
</annotation>
